nfldb/__init__.py
nfldb/category.py
nfldb/db.py
nfldb/query.py
nfldb/sql.py
nfldb/team.py
nfldb/types.py
nfldb/update.py
nfldb/version.py
nfldb3-0.0.1.data/data/share/doc/nfldb/README.md
nfldb3-0.0.1.data/data/share/doc/nfldb/UNLICENSE
nfldb3-0.0.1.data/data/share/doc/nfldb/longdesc.rst
nfldb3-0.0.1.data/data/share/nfldb/config.ini.sample
nfldb3-0.0.1.data/scripts/nfldb-update
nfldb3-0.0.1.dist-info/COPYING
nfldb3-0.0.1.dist-info/METADATA
nfldb3-0.0.1.dist-info/WHEEL
nfldb3-0.0.1.dist-info/top_level.txt
nfldb3-0.0.1.dist-info/RECORD
