Metadata-Version: 2.1
Name: nfldb3
Version: 0.0.1
Summary: A library to manage and update NFL data in a Postgres database updated for Python 3.8. Based on code written byAndrew Gallant.
Home-page: https://github.com/BurntSushi/nfldb
Author: Nick Zeak
Author-email: nczeak@gmail.com
License: UNLICENSE
Platform: ANY
Classifier: License :: Public Domain
Classifier: Development Status :: 3 - Alpha
Classifier: Environment :: Console
Classifier: Intended Audience :: Developers
Classifier: Intended Audience :: End Users/Desktop
Classifier: Intended Audience :: Other Audience
Classifier: Operating System :: OS Independent
Classifier: Programming Language :: Python :: 3.8
Classifier: Topic :: Database
Requires-Dist: nflgame (>=1.2.20)
Requires-Dist: psycopg2
Requires-Dist: enum34
Requires-Dist: pytz
